{
    "containers": {
        "header": {
            "label":            "Widget.containerHeader",
            "name":             "Ceres::Header",
            "allowedTypes":     ["header"]
        },
        "footer": {
            "label":            "Widget.containerFooter",
            "name":             "Ceres::Footer",
            "allowedTypes":     ["footer", "structure", "default"]
        },
        "content": [
            {
                "label":        "Widget.containerHomepage",
                "name":         "Ceres::Homepage",
                "allowedTypes": ["default", "image", "text", "structure"]
            }
        ]
    },
    "presets": {
        "header": [
            {
                "label": "Widget.presetHeaderDefault",
                "presetClass": "Ceres\\Widgets\\Presets\\DefaultHeaderPreset"
            }
        ],
        "footer": [
            {
                "label": "Widget.presetFooterDefault",
                "presetClass": "Ceres\\Widgets\\Presets\\DefaultFooterPreset"
            }
        ],
        "content": [
            {
                "label": "Widget.presetHomepageDefault",
                "presetClass": "Ceres\\Widgets\\Presets\\DefaultHomepagePreset"
            }
        ]
    },
    "widgetTypes": [
        {
            "type": "default",
            "label": "Widget.typeDefault"
        },
        {
            "type": "image",
            "label": "Widget.typeImage"
        },
        {
            "type": "text",
            "label": "Widget.typeText"
        },
        {
            "type": "structure",
            "label": "Widget.typeStructure"
        },
        {
            "type": "header",
            "label": "Widget.typeHeader"
        },
        {
            "type": "footer",
            "label": "Widget.typeFooter"
        }
    ]
}