{
    "identifier": "Ceres::ShippingProfileWidget",
    "label": "Widget.shippingProfileLabel",
    "previewImageURL": "/images/widgets/shipping-select.svg",
    "type": "checkout",
    "categories": ["checkout"],
    "position": 100,
    "widgetClass": "Ceres\\Widgets\\Checkout\\ShippingProfileWidget",
    "settings": {
        "appearance": {
            "type": "select",
            "required": true,
            "defaultValue": "primary",
            "options": "@include(appearance)"
        },
        "hinttext": {
            "type": "codeEditor",
            "defaultValue": "",
            "options": {
                "name": "Widget.shippingProfileHinttextLabel",
                "tooltipText": "Widget.shippingProfileHinttextTooltip"
            }
        }
    }
}
